cobjectric/__init__.py
cobjectric/py.typed
cobjectric-1.0.1.dist-info/WHEEL
cobjectric-1.0.1.dist-info/METADATA
cobjectric-1.0.1.dist-info/RECORD
