Metadata-Version: 2.4
Name: cobjectric
Version: 1.0.1
Summary: Complex Object Metric - A library for measuring complexity of Python objects
Keywords: metrics,json,comparison,machine-learning,evaluation
Author: Nigiva
Author-email: Nigiva <contact@nigiva.com>
License-Expression: MIT
Classifier: Development Status :: 3 - Alpha
Classifier: Intended Audience :: Developers
Classifier: License :: OSI Approved :: MIT License
Classifier: Operating System :: OS Independent
Classifier: Programming Language :: Python :: 3
Classifier: Programming Language :: Python :: 3.13
Classifier: Topic :: Software Development :: Libraries :: Python Modules
Classifier: Typing :: Typed
Requires-Dist: rapidfuzz>=3.14.3
Requires-Python: >=3.13
Project-URL: Documentation, https://github.com/nigiva/cobjectric#readme
Project-URL: Homepage, https://github.com/nigiva/cobjectric
Project-URL: Issues, https://github.com/nigiva/cobjectric/issues
Project-URL: Repository, https://github.com/nigiva/cobjectric.git
